{"data": {"timestamp_sec": 191, "timestamp_ns": 989995708, "steering_angle": -0.013718771748244762}}
{"data": {"timestamp_sec": 192, "timestamp_ns": 989995686, "steering_angle": -0.013718771748244762}}
{"data": {"timestamp_sec": 193, "timestamp_ns": 989995663, "steering_angle": -0.013718771748244762}}
{"data": {"timestamp_sec": 194, "timestamp_ns": 989995641, "steering_angle": -0.013718771748244762}}
{"data": {"timestamp_sec": 198, "timestamp_ns": 989995552, "steering_angle": 0.020384684205055237}}
{"data": {"timestamp_sec": 199, "timestamp_ns": 989995529, "steering_angle": 0.05226325988769531}}
{"data": {"timestamp_sec": 200, "timestamp_ns": 989995507, "steering_angle": 0.042545244097709656}}
{"data": {"timestamp_sec": 201, "timestamp_ns": 989995485, "steering_angle": 0.017871595919132233}}
{"data": {"timestamp_sec": 202, "timestamp_ns": 989995462, "steering_angle": 0.0012967969523742795}}
{"data": {"timestamp_sec": 203, "timestamp_ns": 989995440, "steering_angle": -0.0033564043696969748}}
{"data": {"timestamp_sec": 204, "timestamp_ns": 989995418, "steering_angle": -0.003228704445064068}}
{"data": {"timestamp_sec": 205, "timestamp_ns": 989995395, "steering_angle": -0.003128408920019865}}
{"data": {"timestamp_sec": 206, "timestamp_ns": 989995373, "steering_angle": -0.00278518907725811}}
{"data": {"timestamp_sec": 207, "timestamp_ns": 989995351, "steering_angle": -0.0022640277165919542}}
{"data": {"timestamp_sec": 208, "timestamp_ns": 989995328, "steering_angle": 0.0003523178747855127}}
{"data": {"timestamp_sec": 209, "timestamp_ns": 989995306, "steering_angle": 0.0021633137948811054}}
{"data": {"timestamp_sec": 210, "timestamp_ns": 989995284, "steering_angle": 0.002781652845442295}}
{"data": {"timestamp_sec": 211, "timestamp_ns": 989995261, "steering_angle": 0.0018430911004543304}}
{"data": {"timestamp_sec": 212, "timestamp_ns": 989995239, "steering_angle": 0.000999563024379313}}
{"data": {"timestamp_sec": 213, "timestamp_ns": 989995216, "steering_angle": -0.00018516290583647788}}
{"data": {"timestamp_sec": 214, "timestamp_ns": 989995194, "steering_angle": 0.00047454872401431203}}
{"data": {"timestamp_sec": 215, "timestamp_ns": 989995172, "steering_angle": -0.00010816436406457797}}
{"data": {"timestamp_sec": 216, "timestamp_ns": 989995149, "steering_angle": -0.00035541574470698833}}
{"data": {"timestamp_sec": 217, "timestamp_ns": 989995127, "steering_angle": -2.064140971924644e-05}}
{"data": {"timestamp_sec": 218, "timestamp_ns": 989995105, "steering_angle": 0.0005562080768868327}}
{"data": {"timestamp_sec": 219, "timestamp_ns": 989995082, "steering_angle": 0.0018231319263577461}}
{"data": {"timestamp_sec": 220, "timestamp_ns": 989995060, "steering_angle": -0.002790002152323723}}
{"data": {"timestamp_sec": 221, "timestamp_ns": 989995038, "steering_angle": -0.0377233549952507}}
{"data": {"timestamp_sec": 222, "timestamp_ns": 989995015, "steering_angle": -0.08320233970880508}}
{"data": {"timestamp_sec": 223, "timestamp_ns": 989994993, "steering_angle": -0.062170661985874176}}
{"data": {"timestamp_sec": 224, "timestamp_ns": 989994971, "steering_angle": -0.07351658493280411}}
{"data": {"timestamp_sec": 225, "timestamp_ns": 989994948, "steering_angle": -0.09533929079771042}}
{"data": {"timestamp_sec": 226, "timestamp_ns": 989994926, "steering_angle": -0.12343879789113998}}
{"data": {"timestamp_sec": 227, "timestamp_ns": 989994904, "steering_angle": -0.15057052671909332}}
{"data": {"timestamp_sec": 228, "timestamp_ns": 989994881, "steering_angle": -0.14438976347446442}}
{"data": {"timestamp_sec": 229, "timestamp_ns": 989994859, "steering_angle": -0.12723809480667114}}
{"data": {"timestamp_sec": 230, "timestamp_ns": 989994836, "steering_angle": -0.12516148388385773}}
{"data": {"timestamp_sec": 231, "timestamp_ns": 989994814, "steering_angle": -0.10835375636816025}}
{"data": {"timestamp_sec": 232, "timestamp_ns": 989994792, "steering_angle": -0.05627792328596115}}
{"data": {"timestamp_sec": 233, "timestamp_ns": 989994769, "steering_angle": -0.011916860938072205}}
{"data": {"timestamp_sec": 234, "timestamp_ns": 989994747, "steering_angle": -0.005342454649507999}}
{"data": {"timestamp_sec": 235, "timestamp_ns": 989994725, "steering_angle": -0.00386950746178627}}
{"data": {"timestamp_sec": 236, "timestamp_ns": 989994702, "steering_angle": -0.002133553382009268}}
{"data": {"timestamp_sec": 237, "timestamp_ns": 989994680, "steering_angle": 0.0002973720838781446}}
{"data": {"timestamp_sec": 238, "timestamp_ns": 989994658, "steering_angle": 0.0007806206704117358}}
{"data": {"timestamp_sec": 239, "timestamp_ns": 989994635, "steering_angle": 0.0012504096375778317}}
{"data": {"timestamp_sec": 240, "timestamp_ns": 989994613, "steering_angle": 8.998123666970059e-05}}
{"data": {"timestamp_sec": 241, "timestamp_ns": 989994591, "steering_angle": -0.00021228817058727145}}
{"data": {"timestamp_sec": 242, "timestamp_ns": 989994568, "steering_angle": -0.0003239787765778601}}
{"data": {"timestamp_sec": 243, "timestamp_ns": 989994546, "steering_angle": -7.937225018395111e-05}}
{"data": {"timestamp_sec": 244, "timestamp_ns": 989994524, "steering_angle": 0.0002375748590566218}}
{"data": {"timestamp_sec": 245, "timestamp_ns": 989994501, "steering_angle": -0.000102944606624078}}
{"data": {"timestamp_sec": 246, "timestamp_ns": 989994479, "steering_angle": 0.00023288922966457903}}
{"data": {"timestamp_sec": 247, "timestamp_ns": 989994456, "steering_angle": -0.0002357050689170137}}
{"data": {"timestamp_sec": 248, "timestamp_ns": 989994434, "steering_angle": -0.00011531380005180836}}
{"data": {"timestamp_sec": 249, "timestamp_ns": 989994412, "steering_angle": 0.0024562536273151636}}
{"data": {"timestamp_sec": 250, "timestamp_ns": 989994389, "steering_angle": 0.0278746597468853}}
{"data": {"timestamp_sec": 251, "timestamp_ns": 989994367, "steering_angle": 0.07009882479906082}}
{"data": {"timestamp_sec": 252, "timestamp_ns": 989994345, "steering_angle": 0.11411286145448685}}
{"data": {"timestamp_sec": 253, "timestamp_ns": 989994322, "steering_angle": 0.13382118940353394}}
{"data": {"timestamp_sec": 254, "timestamp_ns": 989994300, "steering_angle": 0.14001287519931793}}
{"data": {"timestamp_sec": 255, "timestamp_ns": 989994278, "steering_angle": 0.15050779283046722}}
{"data": {"timestamp_sec": 256, "timestamp_ns": 989994255, "steering_angle": 0.1587853580713272}}
{"data": {"timestamp_sec": 257, "timestamp_ns": 989994233, "steering_angle": 0.18854273855686188}}
{"data": {"timestamp_sec": 258, "timestamp_ns": 989994211, "steering_angle": 0.18656407296657562}}
{"data": {"timestamp_sec": 259, "timestamp_ns": 989994188, "steering_angle": 0.18644486367702484}}
{"data": {"timestamp_sec": 260, "timestamp_ns": 989994166, "steering_angle": 0.18668827414512634}}
{"data": {"timestamp_sec": 261, "timestamp_ns": 989994144, "steering_angle": 0.19272026419639587}}
{"data": {"timestamp_sec": 262, "timestamp_ns": 989994121, "steering_angle": 0.1564614325761795}}
{"data": {"timestamp_sec": 263, "timestamp_ns": 989994099, "steering_angle": 0.092740997672081}}
{"data": {"timestamp_sec": 264, "timestamp_ns": 989994077, "steering_angle": 0.03896684944629669}}
{"data": {"timestamp_sec": 265, "timestamp_ns": 989994054, "steering_angle": 0.008838510140776634}}
{"data": {"timestamp_sec": 266, "timestamp_ns": 989994032, "steering_angle": 0.0007784938206896186}}
{"data": {"timestamp_sec": 267, "timestamp_ns": 989994009, "steering_angle": -0.00139295042026788}}
{"data": {"timestamp_sec": 268, "timestamp_ns": 989993987, "steering_angle": -5.860830788151361e-05}}
{"data": {"timestamp_sec": 269, "timestamp_ns": 989993965, "steering_angle": 0.0017623098101466894}}
{"data": {"timestamp_sec": 270, "timestamp_ns": 989993942, "steering_angle": -1.9807612261502072e-05}}
{"data": {"timestamp_sec": 271, "timestamp_ns": 989993920, "steering_angle": -0.0012540379539132118}}
{"data": {"timestamp_sec": 272, "timestamp_ns": 989993898, "steering_angle": -0.001322224154137075}}
{"data": {"timestamp_sec": 273, "timestamp_ns": 989993875, "steering_angle": -0.0004206775047350675}}
{"data": {"timestamp_sec": 274, "timestamp_ns": 989993853, "steering_angle": 8.352219447260723e-05}}
{"data": {"timestamp_sec": 275, "timestamp_ns": 989993831, "steering_angle": -0.00010667023889254779}}
{"data": {"timestamp_sec": 276, "timestamp_ns": 989993808, "steering_angle": -5.998723645461723e-05}}
{"data": {"timestamp_sec": 277, "timestamp_ns": 989993786, "steering_angle": -0.00012856909597758204}}
{"data": {"timestamp_sec": 278, "timestamp_ns": 989993764, "steering_angle": 0.00016495307500008494}}
{"data": {"timestamp_sec": 279, "timestamp_ns": 989993741, "steering_angle": 0.0006578153697773814}}
{"data": {"timestamp_sec": 280, "timestamp_ns": 989993719, "steering_angle": 0.000416935101384297}}
{"data": {"timestamp_sec": 281, "timestamp_ns": 989993697, "steering_angle": -0.010869357734918594}}
{"data": {"timestamp_sec": 282, "timestamp_ns": 989993674, "steering_angle": -0.018810540437698364}}
{"data": {"timestamp_sec": 283, "timestamp_ns": 989993652, "steering_angle": 0.0013973803725093603}}
{"data": {"timestamp_sec": 284, "timestamp_ns": 989993629, "steering_angle": 0.013771348632872105}}
{"data": {"timestamp_sec": 285, "timestamp_ns": 989993607, "steering_angle": 0.0049444460310041904}}
{"data": {"timestamp_sec": 286, "timestamp_ns": 989993585, "steering_angle": 0.002743188990280032}}
{"data": {"timestamp_sec": 287, "timestamp_ns": 989993562, "steering_angle": -4.833608181797899e-05}}
{"data": {"timestamp_sec": 288, "timestamp_ns": 989993540, "steering_angle": -0.0022564020473510027}}
{"data": {"timestamp_sec": 289, "timestamp_ns": 989993518, "steering_angle": -0.0011996565153822303}}
{"data": {"timestamp_sec": 290, "timestamp_ns": 989993495, "steering_angle": -0.012629859149456024}}
{"data": {"timestamp_sec": 291, "timestamp_ns": 989993473, "steering_angle": 0.007122687064111233}}
{"data": {"timestamp_sec": 292, "timestamp_ns": 989993451, "steering_angle": -0.0014345574891194701}}
{"data": {"timestamp_sec": 293, "timestamp_ns": 989993428, "steering_angle": -0.010023094713687897}}
{"data": {"timestamp_sec": 294, "timestamp_ns": 989993406, "steering_angle": 0.008487841114401817}}
{"data": {"timestamp_sec": 295, "timestamp_ns": 989993384, "steering_angle": -0.0013014459982514381}}
{"data": {"timestamp_sec": 296, "timestamp_ns": 989993361, "steering_angle": -0.0014360517961904407}}
{"data": {"timestamp_sec": 297, "timestamp_ns": 989993339, "steering_angle": 0.007275709416717291}}
{"data": {"timestamp_sec": 298, "timestamp_ns": 989993317, "steering_angle": -0.02157733403146267}}
{"data": {"timestamp_sec": 299, "timestamp_ns": 989993294, "steering_angle": 0.014017093926668167}}
{"data": {"timestamp_sec": 300, "timestamp_ns": 989993272, "steering_angle": 0.011847426183521748}}
{"data": {"timestamp_sec": 301, "timestamp_ns": 989993249, "steering_angle": -7.756629202049226e-05}}
{"data": {"timestamp_sec": 302, "timestamp_ns": 989993227, "steering_angle": 0.0053404513746500015}}
{"data": {"timestamp_sec": 303, "timestamp_ns": 989993205, "steering_angle": -0.009465442039072514}}
{"data": {"timestamp_sec": 304, "timestamp_ns": 989993182, "steering_angle": 0.002150275744497776}}
{"data": {"timestamp_sec": 305, "timestamp_ns": 989993160, "steering_angle": -0.007092613261193037}}
{"data": {"timestamp_sec": 306, "timestamp_ns": 989993138, "steering_angle": 0.012904254719614983}}
{"data": {"timestamp_sec": 307, "timestamp_ns": 989993115, "steering_angle": 0.0015432897489517927}}
{"data": {"timestamp_sec": 308, "timestamp_ns": 989993093, "steering_angle": 0.013707286678254604}}
{"data": {"timestamp_sec": 309, "timestamp_ns": 989993071, "steering_angle": -0.00960682425647974}}
{"data": {"timestamp_sec": 310, "timestamp_ns": 989993048, "steering_angle": -0.02660159021615982}}
{"data": {"timestamp_sec": 311, "timestamp_ns": 989993026, "steering_angle": -0.021328480914235115}}
{"data": {"timestamp_sec": 312, "timestamp_ns": 989993004, "steering_angle": -0.001557379961013794}}
{"data": {"timestamp_sec": 313, "timestamp_ns": 989992981, "steering_angle": -0.004259817767888308}}
{"data": {"timestamp_sec": 314, "timestamp_ns": 989992959, "steering_angle": -0.0024055433459579945}}
{"data": {"timestamp_sec": 315, "timestamp_ns": 989992937, "steering_angle": 0.0002156111440854147}}
{"data": {"timestamp_sec": 316, "timestamp_ns": 989992914, "steering_angle": 0.0028898403979837894}}
{"data": {"timestamp_sec": 317, "timestamp_ns": 989992892, "steering_angle": 0.003487569047138095}}
{"data": {"timestamp_sec": 318, "timestamp_ns": 989992870, "steering_angle": 0.013267682865262032}}
{"data": {"timestamp_sec": 319, "timestamp_ns": 989992847, "steering_angle": 0.018135616555809975}}
{"data": {"timestamp_sec": 320, "timestamp_ns": 989992825, "steering_angle": 0.02009015716612339}}
{"data": {"timestamp_sec": 321, "timestamp_ns": 989992802, "steering_angle": 0.016716012731194496}}
{"data": {"timestamp_sec": 322, "timestamp_ns": 989992780, "steering_angle": 0.014949929900467396}}
{"data": {"timestamp_sec": 323, "timestamp_ns": 989992758, "steering_angle": 0.012470348738133907}}
{"data": {"timestamp_sec": 324, "timestamp_ns": 989992735, "steering_angle": 0.004162603989243507}}
{"data": {"timestamp_sec": 325, "timestamp_ns": 989992713, "steering_angle": 0.005111653357744217}}
{"data": {"timestamp_sec": 326, "timestamp_ns": 989992691, "steering_angle": 0.00434928759932518}}
{"data": {"timestamp_sec": 327, "timestamp_ns": 989992668, "steering_angle": 0.0026551000773906708}}
{"data": {"timestamp_sec": 328, "timestamp_ns": 989992646, "steering_angle": 0.0022601240780204535}}
{"data": {"timestamp_sec": 329, "timestamp_ns": 989992624, "steering_angle": 0.0013038625475019217}}
{"data": {"timestamp_sec": 330, "timestamp_ns": 989992601, "steering_angle": 0.001551411347463727}}
{"data": {"timestamp_sec": 331, "timestamp_ns": 989992579, "steering_angle": 0.0025662227999418974}}
{"data": {"timestamp_sec": 332, "timestamp_ns": 989992557, "steering_angle": 0.002224111231043935}}
{"data": {"timestamp_sec": 333, "timestamp_ns": 989992534, "steering_angle": -0.001567928702570498}}
{"data": {"timestamp_sec": 334, "timestamp_ns": 989992512, "steering_angle": -0.020139003172516823}}
{"data": {"timestamp_sec": 335, "timestamp_ns": 989992490, "steering_angle": -0.060149140655994415}}
{"data": {"timestamp_sec": 336, "timestamp_ns": 989992467, "steering_angle": -0.10064584016799927}}
{"data": {"timestamp_sec": 337, "timestamp_ns": 989992445, "steering_angle": -0.04743864759802818}}
{"data": {"timestamp_sec": 338, "timestamp_ns": 989992422, "steering_angle": -0.04796122387051582}}
{"data": {"timestamp_sec": 339, "timestamp_ns": 989992400, "steering_angle": -0.04796122387051582}}
{"data": {"timestamp_sec": 340, "timestamp_ns": 989992378, "steering_angle": -0.04742219299077988}}
{"data": {"timestamp_sec": 341, "timestamp_ns": 989992355, "steering_angle": -0.04522813856601715}}
{"data": {"timestamp_sec": 342, "timestamp_ns": 989992333, "steering_angle": -0.08555156737565994}}
{"data": {"timestamp_sec": 343, "timestamp_ns": 989992311, "steering_angle": -0.16780956089496613}}
{"data": {"timestamp_sec": 344, "timestamp_ns": 989992288, "steering_angle": -0.1971377581357956}}
{"data": {"timestamp_sec": 345, "timestamp_ns": 989992266, "steering_angle": -0.20921552181243896}}
{"data": {"timestamp_sec": 346, "timestamp_ns": 989992244, "steering_angle": -0.20386525988578796}}
{"data": {"timestamp_sec": 347, "timestamp_ns": 989992221, "steering_angle": -0.19744795560836792}}
{"data": {"timestamp_sec": 348, "timestamp_ns": 989992199, "steering_angle": -0.17162993550300598}}
{"data": {"timestamp_sec": 349, "timestamp_ns": 989992177, "steering_angle": -0.12200120836496353}}
{"data": {"timestamp_sec": 350, "timestamp_ns": 989992154, "steering_angle": -0.07562411576509476}}
{"data": {"timestamp_sec": 351, "timestamp_ns": 989992132, "steering_angle": -0.04754092916846275}}
{"data": {"timestamp_sec": 352, "timestamp_ns": 989992110, "steering_angle": -0.029013382270932198}}
{"data": {"timestamp_sec": 353, "timestamp_ns": 989992087, "steering_angle": -0.014126922935247421}}
{"data": {"timestamp_sec": 354, "timestamp_ns": 989992065, "steering_angle": -0.004075225908309221}}
{"data": {"timestamp_sec": 355, "timestamp_ns": 989992043, "steering_angle": 0.0012486845953390002}}
{"data": {"timestamp_sec": 356, "timestamp_ns": 989992020, "steering_angle": -0.0012871696380898356}}
{"data": {"timestamp_sec": 357, "timestamp_ns": 989991998, "steering_angle": -0.0034801550209522247}}
{"data": {"timestamp_sec": 358, "timestamp_ns": 989991975, "steering_angle": -0.009827679954469204}}
{"data": {"timestamp_sec": 359, "timestamp_ns": 989991953, "steering_angle": -0.011749007739126682}}
{"data": {"timestamp_sec": 360, "timestamp_ns": 989991931, "steering_angle": -0.012060144916176796}}
{"data": {"timestamp_sec": 361, "timestamp_ns": 989991908, "steering_angle": -0.06545261293649673}}
{"data": {"timestamp_sec": 362, "timestamp_ns": 989991886, "steering_angle": -0.0015619307523593307}}
{"data": {"timestamp_sec": 363, "timestamp_ns": 989991864, "steering_angle": -0.023156143724918365}}
{"data": {"timestamp_sec": 364, "timestamp_ns": 989991841, "steering_angle": -0.0021194282453507185}}
{"data": {"timestamp_sec": 365, "timestamp_ns": 989991819, "steering_angle": 0.012201833538711071}}
{"data": {"timestamp_sec": 366, "timestamp_ns": 989991797, "steering_angle": 0.01441851258277893}}
{"data": {"timestamp_sec": 367, "timestamp_ns": 989991774, "steering_angle": 0.015365191735327244}}
{"data": {"timestamp_sec": 368, "timestamp_ns": 989991752, "steering_angle": 0.007635329384356737}}
{"data": {"timestamp_sec": 369, "timestamp_ns": 989991730, "steering_angle": 0.008495901711285114}}
{"data": {"timestamp_sec": 370, "timestamp_ns": 989991707, "steering_angle": 0.011291785165667534}}
{"data": {"timestamp_sec": 371, "timestamp_ns": 989991685, "steering_angle": 0.005791304167360067}}
{"data": {"timestamp_sec": 372, "timestamp_ns": 989991663, "steering_angle": 0.005519535392522812}}
{"data": {"timestamp_sec": 373, "timestamp_ns": 989991640, "steering_angle": 0.0035002806689590216}}
{"data": {"timestamp_sec": 374, "timestamp_ns": 989991618, "steering_angle": 0.003907003905624151}}
{"data": {"timestamp_sec": 375, "timestamp_ns": 989991595, "steering_angle": 0.0023635237012058496}}
{"data": {"timestamp_sec": 376, "timestamp_ns": 989991573, "steering_angle": 0.0008329565753228962}}
{"data": {"timestamp_sec": 377, "timestamp_ns": 989991551, "steering_angle": 0.00011576472024898976}}
{"data": {"timestamp_sec": 378, "timestamp_ns": 989991528, "steering_angle": -0.00017720261530485004}}
{"data": {"timestamp_sec": 379, "timestamp_ns": 989991506, "steering_angle": -0.0007646380108781159}}
{"data": {"timestamp_sec": 380, "timestamp_ns": 989991484, "steering_angle": -0.0011262947227805853}}
{"data": {"timestamp_sec": 381, "timestamp_ns": 989991461, "steering_angle": -0.000706065446138382}}
{"data": {"timestamp_sec": 382, "timestamp_ns": 989991439, "steering_angle": -0.0051912167109549046}}
{"data": {"timestamp_sec": 383, "timestamp_ns": 989991417, "steering_angle": -0.04475511237978935}}
{"data": {"timestamp_sec": 384, "timestamp_ns": 989991394, "steering_angle": -0.11632996052503586}}
{"data": {"timestamp_sec": 385, "timestamp_ns": 989991372, "steering_angle": -0.1976599544286728}}
{"data": {"timestamp_sec": 386, "timestamp_ns": 989991350, "steering_angle": -0.2406037300825119}}
{"data": {"timestamp_sec": 387, "timestamp_ns": 989991327, "steering_angle": -0.21475650370121002}}
{"data": {"timestamp_sec": 388, "timestamp_ns": 989991305, "steering_angle": -0.15654107928276062}}
{"data": {"timestamp_sec": 389, "timestamp_ns": 989991283, "steering_angle": -0.09794340282678604}}
{"data": {"timestamp_sec": 390, "timestamp_ns": 989991260, "steering_angle": -0.0526982843875885}}
{"data": {"timestamp_sec": 391, "timestamp_ns": 989991238, "steering_angle": -0.037692841142416}}
{"data": {"timestamp_sec": 392, "timestamp_ns": 989991215, "steering_angle": -0.00570931239053607}}
{"data": {"timestamp_sec": 393, "timestamp_ns": 989991193, "steering_angle": -0.001348851015791297}}
{"data": {"timestamp_sec": 394, "timestamp_ns": 989991171, "steering_angle": 0.0006162940990179777}}
{"data": {"timestamp_sec": 395, "timestamp_ns": 989991148, "steering_angle": 0.0003956806904170662}}
{"data": {"timestamp_sec": 396, "timestamp_ns": 989991126, "steering_angle": 0.000557715306058526}}
{"data": {"timestamp_sec": 397, "timestamp_ns": 989991104, "steering_angle": 0.0008524549775756896}}
{"data": {"timestamp_sec": 398, "timestamp_ns": 989991081, "steering_angle": -0.0003412871155887842}}
{"data": {"timestamp_sec": 399, "timestamp_ns": 989991059, "steering_angle": 0.00017662059690337628}}
{"data": {"timestamp_sec": 400, "timestamp_ns": 989991037, "steering_angle": 0.0002855191414710134}}
{"data": {"timestamp_sec": 401, "timestamp_ns": 989991014, "steering_angle": -0.00030527188209816813}}
{"data": {"timestamp_sec": 402, "timestamp_ns": 989990992, "steering_angle": 0.0005445342976599932}}
{"data": {"timestamp_sec": 403, "timestamp_ns": 989990970, "steering_angle": 0.00018858708790503442}}
{"data": {"timestamp_sec": 404, "timestamp_ns": 989990947, "steering_angle": -6.490311352536082e-05}}
{"data": {"timestamp_sec": 405, "timestamp_ns": 989990925, "steering_angle": -0.0006428263732232153}}
{"data": {"timestamp_sec": 406, "timestamp_ns": 989990903, "steering_angle": -0.0008482107077725232}}
{"data": {"timestamp_sec": 407, "timestamp_ns": 989990880, "steering_angle": 0.0003581915225367993}}
{"data": {"timestamp_sec": 408, "timestamp_ns": 989990858, "steering_angle": -0.0005415985360741615}}
{"data": {"timestamp_sec": 409, "timestamp_ns": 989990836, "steering_angle": 0.00046926335198804736}}
{"data": {"timestamp_sec": 410, "timestamp_ns": 989990813, "steering_angle": -0.00045174642582423985}}
{"data": {"timestamp_sec": 411, "timestamp_ns": 989990791, "steering_angle": 0.00016722518194001168}}
{"data": {"timestamp_sec": 412, "timestamp_ns": 989990768, "steering_angle": -3.248600842198357e-05}}
{"data": {"timestamp_sec": 413, "timestamp_ns": 989990746, "steering_angle": -9.72699563135393e-05}}
{"data": {"timestamp_sec": 414, "timestamp_ns": 989990724, "steering_angle": -0.00016666682495269924}}
{"data": {"timestamp_sec": 415, "timestamp_ns": 989990701, "steering_angle": 0.00013279891572892666}}
{"data": {"timestamp_sec": 416, "timestamp_ns": 989990679, "steering_angle": -0.0003503485058899969}}
{"data": {"timestamp_sec": 417, "timestamp_ns": 989990657, "steering_angle": -4.3813335651066154e-05}}
{"data": {"timestamp_sec": 418, "timestamp_ns": 989990634, "steering_angle": 0.00046462847967632115}}
{"data": {"timestamp_sec": 419, "timestamp_ns": 989990612, "steering_angle": -0.00029202611767686903}}
{"data": {"timestamp_sec": 420, "timestamp_ns": 989990590, "steering_angle": 0.000100202982139308}}
{"data": {"timestamp_sec": 421, "timestamp_ns": 989990567, "steering_angle": 6.003181260894053e-05}}
{"data": {"timestamp_sec": 422, "timestamp_ns": 989990545, "steering_angle": -0.00011440708476584405}}
{"data": {"timestamp_sec": 423, "timestamp_ns": 989990523, "steering_angle": -0.0001341040333500132}}
{"data": {"timestamp_sec": 424, "timestamp_ns": 989990500, "steering_angle": 0.0003707458672579378}}
{"data": {"timestamp_sec": 425, "timestamp_ns": 989990478, "steering_angle": 2.1439980173454387e-06}}
{"data": {"timestamp_sec": 426, "timestamp_ns": 989990456, "steering_angle": -0.000683418707922101}}
{"data": {"timestamp_sec": 427, "timestamp_ns": 989990433, "steering_angle": -0.00024060177383944392}}
{"data": {"timestamp_sec": 428, "timestamp_ns": 989990411, "steering_angle": 0.00025377413840033114}}
{"data": {"timestamp_sec": 429, "timestamp_ns": 989990388, "steering_angle": 0.00020642737217713147}}
{"data": {"timestamp_sec": 430, "timestamp_ns": 989990366, "steering_angle": -0.0005965824821032584}}
{"data": {"timestamp_sec": 431, "timestamp_ns": 989990344, "steering_angle": 1.919893293234054e-05}}
{"data": {"timestamp_sec": 432, "timestamp_ns": 989990321, "steering_angle": 0.0002970246714539826}}
{"data": {"timestamp_sec": 433, "timestamp_ns": 989990299, "steering_angle": 0.0002729415718931705}}
{"data": {"timestamp_sec": 434, "timestamp_ns": 989990277, "steering_angle": -0.0009740295354276896}}
{"data": {"timestamp_sec": 435, "timestamp_ns": 989990254, "steering_angle": -0.0013410651590675116}}
{"data": {"timestamp_sec": 436, "timestamp_ns": 989990232, "steering_angle": -0.0003390209749341011}}
{"data": {"timestamp_sec": 437, "timestamp_ns": 949990211, "steering_angle": 0.00031012267572805285}}
